[
  {
    "value": 0,
    "label": "12:00 AM"
  },
  {
    "value": 1800,
    "label": "12:30 AM"
  },
  {
    "value": 3600,
    "label": "01:00 AM"
  },
  {
    "value": 5400,
    "label": "01:30 AM"
  },
  {
    "value": 7200,
    "label": "02:00 AM"
  },
  {
    "value": 9000,
    "label": "02:30 AM"
  },
  {
    "value": 10800,
    "label": "03:00 AM"
  },
  {
    "value": 12600,
    "label": "03:30 AM"
  },
  {
    "value": 14400,
    "label": "04:00 AM"
  },
  {
    "value": 16200,
    "label": "04:30 AM"
  },
  {
    "value": 18000,
    "label": "05:00 AM"
  },
  {
    "value": 19800,
    "label": "05:30 AM"
  },
  {
    "value": 21600,
    "label": "06:00 AM"
  },
  {
    "value": 23400,
    "label": "06:30 AM"
  },
  {
    "value": 25200,
    "label": "07:00 AM"
  },
  {
    "value": 27000,
    "label": "07:30 AM"
  },
  {
    "value": 28800,
    "label": "08:00 AM"
  },
  {
    "value": 30600,
    "label": "08:30 AM"
  },
  {
    "value": 32400,
    "label": "09:00 AM"
  },
  {
    "value": 34200,
    "label": "09:30 AM"
  },
  {
    "value": 36000,
    "label": "10:00 AM"
  },
  {
    "value": 37800,
    "label": "10:30 AM"
  },
  {
    "value": 39600,
    "label": "11:00 AM"
  },
  {
    "value": 41400,
    "label": "11:30 AM"
  },
  {
    "value": 43200,
    "label": "12:00 PM"
  },
  {
    "value": 45000,
    "label": "12:30 PM"
  },
  {
    "value": 46800,
    "label": "01:00 PM"
  },
  {
    "value": 48600,
    "label": "01:30 PM"
  },
  {
    "value": 50400,
    "label": "02:00 PM"
  },
  {
    "value": 52200,
    "label": "02:30 PM"
  },
  {
    "value": 54000,
    "label": "03:00 PM"
  },
  {
    "value": 55800,
    "label": "03:30 PM"
  },
  {
    "value": 57600,
    "label": "04:00 PM"
  },
  {
    "value": 59400,
    "label": "04:30 PM"
  },
  {
    "value": 61200,
    "label": "05:00 PM"
  },
  {
    "value": 63000,
    "label": "05:30 PM"
  },
  {
    "value": 64800,
    "label": "06:00 PM"
  },
  {
    "value": 66600,
    "label": "06:30 PM"
  },
  {
    "value": 68400,
    "label": "07:00 PM"
  },
  {
    "value": 70200,
    "label": "07:30 PM"
  },
  {
    "value": 72000,
    "label": "08:00 PM"
  },
  {
    "value": 73800,
    "label": "08:30 PM"
  },
  {
    "value": 75600,
    "label": "09:00 PM"
  },
  {
    "value": 77400,
    "label": "09:30 PM"
  },
  {
    "value": 79200,
    "label": "10:00 PM"
  },
  {
    "value": 81000,
    "label": "10:30 PM"
  },
  {
    "value": 82800,
    "label": "11:00 PM"
  },
  {
    "value": 84600,
    "label": "11:30 PM"
  },
  {
    "value": 86399,
    "label": "11:59 PM"
  }
]